OpenFisca_France_Dotations_Locales-4.10.0.data/data/share/openfisca/openfisca-france-dotations-locales/CHANGELOG.md
OpenFisca_France_Dotations_Locales-4.10.0.data/data/share/openfisca/openfisca-france-dotations-locales/LICENSE
OpenFisca_France_Dotations_Locales-4.10.0.data/data/share/openfisca/openfisca-france-dotations-locales/README.md
OpenFisca_France_Dotations_Locales-4.10.0.data/data/share/openfisca/openfisca-france-dotations-locales/REFERENCES.md
openfisca_france_dotations_locales/__init__.py
openfisca_france_dotations_locales/entities.py
openfisca_france_dotations_locales/units.yaml
openfisca_france_dotations_locales/parameters/dgf_part_ecretement_attribue_df.yaml
openfisca_france_dotations_locales/parameters/montant_dotation_globale_fonctionnement.yaml
openfisca_france_dotations_locales/parameters/dotation_amenagement_communes_outre_mer/montant.yaml
openfisca_france_dotations_locales/parameters/dotation_amenagement_communes_outre_mer/taux_majoration_population.yaml
openfisca_france_dotations_locales/parameters/dotation_communes_nouvelles/montant.yaml
openfisca_france_dotations_locales/parameters/dotation_communes_nouvelles/amorcage/montant.yaml
openfisca_france_dotations_locales/parameters/dotation_communes_nouvelles/amorcage/montant_attribution.yaml
openfisca_france_dotations_locales/parameters/dotation_communes_nouvelles/amorcage/plafond_age_commune.yaml
openfisca_france_dotations_locales/parameters/dotation_communes_nouvelles/amorcage/seuil_age_commune.yaml
openfisca_france_dotations_locales/parameters/dotation_communes_nouvelles/eligibilite/plafond_nombre_habitants.yaml
openfisca_france_dotations_locales/parameters/dotation_communes_nouvelles/garantie/montant.yaml
openfisca_france_dotations_locales/parameters/dotation_forfaitaire/montant.yaml
openfisca_france_dotations_locales/parameters/dotation_forfaitaire/montant_maximum_par_habitant.yaml
openfisca_france_dotations_locales/parameters/dotation_forfaitaire/montant_minimum_par_habitant.yaml
OpenFisca_France_Dotations_Locales-4.10.0.dist-info/LICENSE
OpenFisca_France_Dotations_Locales-4.10.0.dist-info/METADATA
OpenFisca_France_Dotations_Locales-4.10.0.dist-info/WHEEL
OpenFisca_France_Dotations_Locales-4.10.0.dist-info/top_level.txt
OpenFisca_France_Dotations_Locales-4.10.0.dist-info/RECORD
