Metadata-Version: 2.1
Name: OpenFisca-France-Dotations-Locales
Version: 4.10.0
Summary: [EN] OpenFisca tax and benefit system for France State endowments to local authorities.         [FR] Modèle de microsimulation OpenFisca dédié aux dotations de l'État aux collectivités territoriales.
Home-page: https://git.leximpact.dev/leximpact/openfisca-france-dotations-locales
Author: LexImpact Team
Author-email: leximpact@an.fr
License: http://www.fsf.org/licensing/licenses/agpl-3.0.html
Keywords: France microsimulation local tax endowment dotations territoires
Classifier: Development Status :: 5 - Production/Stable
Classifier: License :: OSI Approved :: GNU Affero General Public License v3
Classifier: Operating System :: POSIX
Classifier: Programming Language :: Python
Classifier: Programming Language :: Python :: 3.11
Classifier: Topic :: Scientific/Engineering :: Information Analysis
License-File: LICENSE
Requires-Dist: OpenFisca-Core[web-api]<42.0,>=27.0
Provides-Extra: dev
Requires-Dist: pandas<3.0.0,>=2.2.1; extra == "dev"
Requires-Dist: autopep8<3.0.0,>=2.1.0; extra == "dev"
Requires-Dist: flake8<7.0.0,>=6.0.0; extra == "dev"
Requires-Dist: pycodestyle<3.0,>=2.10.0; extra == "dev"
Requires-Dist: jupyter<2.0.0,>=1.0.0; extra == "dev"
